memfunc/__init__.py
memfunc/linear.py
memfunc/nonlinear.py
memfunc-0.0.1.dist-info/LICENSE
memfunc-0.0.1.dist-info/METADATA
memfunc-0.0.1.dist-info/WHEEL
memfunc-0.0.1.dist-info/top_level.txt
memfunc-0.0.1.dist-info/RECORD
