Metadata-Version: 2.1
Name: memfunc
Version: 0.0.1
Summary: It is used to quickly establish membership functions for subsequent fuzzy transformations.
Home-page: https://github.com/tzamou/memfunc
Author: Guan-Lin Chen
Author-email: ken54787845@gmail.com
Classifier: Programming Language :: Python :: 3
Classifier: License :: OSI Approved :: MIT License
Classifier: Operating System :: OS Independent
Requires-Python: >=3.6
License-File: LICENSE
